{
    "accounts": [
        {
            "account_id": "vovW6J5WEEcG1ZQ3DxE4CNaaeNNwGeiq6GmkG",
            "balances": {
                "available": 100.0,
                "current": 110.0,
                "limit": null,
                "iso_currency_code": "USD",
                "unofficial_currency_code": null
            },
            "mask": "0000",
            "name": "Plaid Checking",
            "official_name": "Plaid Gold Standard 0% Interest Checking",
            "type": "depository",
            "subtype": "checking",
            "holder_category": "personal"
        },
        {
            "account_id": "RpqylAVyWWSnKEkZG9Q5CqJJgqq4pgiapxyb7",
            "balances": {
                "available": 200.0,
                "current": 210.0,
                "limit": null,
                "iso_currency_code": "USD",
                "unofficial_currency_code": null
            },
            "mask": "1111",
            "name": "Plaid Saving",
            "official_name": "Plaid Silver Standard 0.1% Interest Saving",
            "type": "depository",
            "subtype": "savings",
            "holder_category": "personal"
        },
        {
            "account_id": "6Gpbk4mbRRHMbvz1yWB3CR88ZRRwLZc8DaZXr",
            "balances": {
                "available": null,
                "current": 1000.0,
                "limit": null,
                "iso_currency_code": "USD",
                "unofficial_currency_code": null
            },
            "mask": "2222",
            "name": "Plaid CD",
            "official_name": "Plaid Bronze Standard 0.2% Interest CD",
            "type": "depository",
            "subtype": "cd"
        },
        {
            "account_id": "XAxV3R1VyyTaAqv3K9blCXBBpXXvepCbKMZnd",
            "balances": {
                "available": null,
                "current": 410.0,
                "limit": 2000.0,
                "iso_currency_code": "USD",
                "unofficial_currency_code": null
            },
            "mask": "3333",
            "name": "Plaid Credit Card",
            "official_name": "Plaid Diamond 12.5% APR Interest Credit Card",
            "type": "credit",
            "subtype": "credit card"
        },
        {
            "account_id": "DkJzEGRzPPsoWRMAaqE5CPNNKPPLbKc3WlDa3",
            "balances": {
                "available": 43200.0,
                "current": 43200.0,
                "limit": null,
                "iso_currency_code": "USD",
                "unofficial_currency_code": null
            },
            "mask": "4444",
            "name": "Plaid Money Market",
            "official_name": "Plaid Platinum Standard 1.85% Interest Money Market",
            "type": "depository",
            "subtype": "money market"
        },
        {
            "account_id": "VEByzm1ybbu3A9kZNQy5uVBB7VVKE7i9g51Pq",
            "balances": {
                "available": null,
                "current": 320.76,
                "limit": null,
                "iso_currency_code": "USD",
                "unofficial_currency_code": null
            },
            "mask": "5555",
            "name": "Plaid IRA",
            "official_name": null,
            "type": "investment",
            "subtype": "ira"
        },
        {
            "account_id": "wkvX61AXWWsno4k36jGVCJjjXJJp9XfPZywoq",
            "balances": {
                "available": null,
                "current": 23631.9805,
                "limit": null,
                "iso_currency_code": "USD",
                "unofficial_currency_code": null
            },
            "mask": "6666",
            "name": "Plaid 401k",
            "official_name": null,
            "type": "investment",
            "subtype": "401k"
        },
        {
            "account_id": "5AkMXaxMvvTB7Kr91NREhDRRxDDAMxc5K4l7p",
            "balances": {
                "available": null,
                "current": 65262.0,
                "limit": null,
                "iso_currency_code": "USD",
                "unofficial_currency_code": null
            },
            "mask": "7777",
            "name": "Plaid Student Loan",
            "official_name": null,
            "type": "loan",
            "subtype": "student",
            "holder_category": "personal"
        },
        {
            "account_id": "JjJNyWaNMMI7PQAbRkD5CJddxJJ56xfB6K3gZ",
            "balances": {
                "available": null,
                "current": 56302.06,
                "limit": null,
                "iso_currency_code": "USD",
                "unofficial_currency_code": null
            },
            "mask": "8888",
            "name": "Plaid Mortgage",
            "official_name": null,
            "type": "loan",
            "subtype": "mortgage"
        },
        {
            "account_id": "kNvQRobQ77sVE7onb361IaBBxaa91xhL6Gndq",
            "balances": {
                "available": 6009.0,
                "current": 6009.0,
                "limit": null,
                "iso_currency_code": "USD",
                "unofficial_currency_code": null
            },
            "mask": "9001",
            "name": "Plaid HSA",
            "official_name": "Plaid Cares Health Savings Account",
            "type": "depository",
            "subtype": "hsa"
        },
        {
            "account_id": "lP6QRoWQeehMENVr53GlCdXXpdd4DpupozQdM",
            "balances": {
                "available": 12060.0,
                "current": 12060.0,
                "limit": null,
                "iso_currency_code": "USD",
                "unofficial_currency_code": null
            },
            "mask": "9002",
            "name": "Plaid Cash Management",
            "official_name": "Plaid Growth Cash Management",
            "type": "depository",
            "subtype": "cash management"
        },
        {
            "account_id": "qZv16oX1LLhgwz7pqMWnuM44yMMEGytgrvG7x",
            "balances": {
                "available": 4980.0,
                "current": 5020.0,
                "limit": 10000.0,
                "iso_currency_code": "USD",
                "unofficial_currency_code": null
            },
            "mask": "9999",
            "name": "Plaid Business Credit Card",
            "official_name": "Plaid Platinum Small Business Credit Card",
            "type": "credit",
            "subtype": "credit card",
            "holder_category": "business"
        }
    ],
    "transactions": [
        {
            "account_id": "RpqylAVyWWSnKEkZG9Q5CqJJgqq4pgiapxyb7",
            "account_owner": null,
            "amount": 25.0,
            "authorized_date": "2025-07-17",
            "authorized_datetime": null,
            "category": null,
            "category_id": null,
            "check_number": null,
            "counterparties": [],
            "date": "2025-07-18",
            "datetime": null,
            "iso_currency_code": "USD",
            "location": {
                "address": null,
                "city": null,
                "region": null,
                "postal_code": null,
                "country": null,
                "lat": null,
                "lon": null,
                "store_number": null
            },
            "logo_url": null,
            "merchant_entity_id": null,
            "merchant_name": null,
            "name": "CREDIT CARD 3333 PAYMENT *//",
            "payment_channel": "other",
            "payment_meta": {
                "reference_number": null,
                "ppd_id": null,
                "payee": null,
                "by_order_of": null,
                "payer": null,
                "payment_method": null,
                "payment_processor": null,
                "reason": null
            },
            "pending": false,
            "pending_transaction_id": null,
            "personal_finance_category": {
                "confidence_level": "LOW",
                "detailed": "LOAN_PAYMENTS_CREDIT_CARD_PAYMENT",
                "primary": "LOAN_PAYMENTS"
            },
            "personal_finance_category_icon_url": "https://plaid-category-icons.plaid.com/PFC_LOAN_PAYMENTS.png",
            "transaction_code": null,
            "transaction_id": "rMvW6oRWppS8EM6JqBG3TMm38pVBX9u79dgVd",
            "transaction_type": "special",
            "unofficial_currency_code": null,
            "website": null
        },
        {
            "account_id": "vovW6J5WEEcG1ZQ3DxE4CNaaeNNwGeiq6GmkG",
            "account_owner": null,
            "amount": 5.4,
            "authorized_date": "2025-07-17",
            "authorized_datetime": null,
            "category": null,
            "category_id": null,
            "check_number": null,
            "counterparties": [
                {
                    "name": "Uber",
                    "type": "merchant",
                    "website": "uber.com",
                    "logo_url": "https://plaid-merchant-logos.plaid.com/uber_1060.png",
                    "confidence_level": "VERY_HIGH",
                    "entity_id": "eyg8o776k0QmNgVpAmaQj4WgzW9Qzo6O51gdd",
                    "phone_number": null
                }
            ],
            "date": "2025-07-18",
            "datetime": null,
            "iso_currency_code": "USD",
            "location": {
                "address": null,
                "city": null,
                "region": null,
                "postal_code": null,
                "country": null,
                "lat": null,
                "lon": null,
                "store_number": null
            },
            "logo_url": "https://plaid-merchant-logos.plaid.com/uber_1060.png",
            "merchant_entity_id": "eyg8o776k0QmNgVpAmaQj4WgzW9Qzo6O51gdd",
            "merchant_name": "Uber",
            "name": "Uber 063015 SF**POOL**",
            "payment_channel": "online",
            "payment_meta": {
                "reference_number": null,
                "ppd_id": null,
                "payee": null,
                "by_order_of": null,
                "payer": null,
                "payment_method": null,
                "payment_processor": null,
                "reason": null
            },
            "pending": false,
            "pending_transaction_id": null,
            "personal_finance_category": {
                "confidence_level": "VERY_HIGH",
                "detailed": "TRANSPORTATION_TAXIS_AND_RIDE_SHARES",
                "primary": "TRANSPORTATION"
            },
            "personal_finance_category_icon_url": "https://plaid-category-icons.plaid.com/PFC_TRANSPORTATION.png",
            "transaction_code": null,
            "transaction_id": "5AkMXaxMvvTB7Kr91NREhDR4Jv8gjMF5yGMAE",
            "transaction_type": "special",
            "unofficial_currency_code": null,
            "website": "uber.com"
        },
        {
            "account_id": "DkJzEGRzPPsoWRMAaqE5CPNNKPPLbKc3WlDa3",
            "account_owner": null,
            "amount": 5850.0,
            "authorized_date": null,
            "authorized_datetime": null,
            "category": null,
            "category_id": null,
            "check_number": null,
            "counterparties": [],
            "date": "2025-07-17",
            "datetime": null,
            "iso_currency_code": "USD",
            "location": {
                "address": null,
                "city": null,
                "region": null,
                "postal_code": null,
                "country": null,
                "lat": null,
                "lon": null,
                "store_number": null
            },
            "logo_url": null,
            "merchant_entity_id": null,
            "merchant_name": null,
            "name": "ACH Electronic CreditGUSTO PAY 123456",
            "payment_channel": "online",
            "payment_meta": {
                "reference_number": null,
                "ppd_id": null,
                "payee": null,
                "by_order_of": null,
                "payer": null,
                "payment_method": "ACH",
                "payment_processor": null,
                "reason": null
            },
            "pending": false,
            "pending_transaction_id": null,
            "personal_finance_category": {
                "confidence_level": "LOW",
                "detailed": "GENERAL_SERVICES_ACCOUNTING_AND_FINANCIAL_PLANNING",
                "primary": "GENERAL_SERVICES"
            },
            "personal_finance_category_icon_url": "https://plaid-category-icons.plaid.com/PFC_GENERAL_SERVICES.png",
            "transaction_code": null,
            "transaction_id": "P1JZLAeZ88u6l8mQrxb5Ixa4G8nMXeto5XZrB",
            "transaction_type": "special",
            "unofficial_currency_code": null,
            "website": null
        },
        {
            "account_id": "6Gpbk4mbRRHMbvz1yWB3CR88ZRRwLZc8DaZXr",
            "account_owner": null,
            "amount": 1000.0,
            "authorized_date": null,
            "authorized_datetime": null,
            "category": null,
            "category_id": null,
            "check_number": null,
            "counterparties": [],
            "date": "2025-07-17",
            "datetime": null,
            "iso_currency_code": "USD",
            "location": {
                "address": null,
                "city": null,
                "region": null,
                "postal_code": null,
                "country": null,
                "lat": null,
                "lon": null,
                "store_number": null
            },
            "logo_url": null,
            "merchant_entity_id": null,
            "merchant_name": null,
            "name": "CD DEPOSIT .INITIAL.",
            "payment_channel": "other",
            "payment_meta": {
                "reference_number": null,
                "ppd_id": null,
                "payee": null,
                "by_order_of": null,
                "payer": null,
                "payment_method": null,
                "payment_processor": null,
                "reason": null
            },
            "pending": false,
            "pending_transaction_id": null,
            "personal_finance_category": {
                "confidence_level": "LOW",
                "detailed": "GENERAL_MERCHANDISE_OTHER_GENERAL_MERCHANDISE",
                "primary": "GENERAL_MERCHANDISE"
            },
            "personal_finance_category_icon_url": "https://plaid-category-icons.plaid.com/PFC_GENERAL_MERCHANDISE.png",
            "transaction_code": null,
            "transaction_id": "BBJKoWlK44H9z5b8QVLECjqk6m1Qgxu45znNL",
            "transaction_type": "special",
            "unofficial_currency_code": null,
            "website": null
        },
        {
            "account_id": "XAxV3R1VyyTaAqv3K9blCXBBpXXvepCbKMZnd",
            "account_owner": null,
            "amount": 78.5,
            "authorized_date": "2025-07-15",
            "authorized_datetime": null,
            "category": null,
            "category_id": null,
            "check_number": null,
            "counterparties": [],
            "date": "2025-07-16",
            "datetime": null,
            "iso_currency_code": "USD",
            "location": {
                "address": null,
                "city": null,
                "region": null,
                "postal_code": null,
                "country": null,
                "lat": null,
                "lon": null,
                "store_number": null
            },
            "logo_url": null,
            "merchant_entity_id": null,
            "merchant_name": null,
            "name": "Touchstone Climbing",
            "payment_channel": "in store",
            "payment_meta": {
                "reference_number": null,
                "ppd_id": null,
                "payee": null,
                "by_order_of": null,
                "payer": null,
                "payment_method": null,
                "payment_processor": null,
                "reason": null
            },
            "pending": false,
            "pending_transaction_id": null,
            "personal_finance_category": {
                "confidence_level": "LOW",
                "detailed": "PERSONAL_CARE_GYMS_AND_FITNESS_CENTERS",
                "primary": "PERSONAL_CARE"
            },
            "personal_finance_category_icon_url": "https://plaid-category-icons.plaid.com/PFC_PERSONAL_CARE.png",
            "transaction_code": null,
            "transaction_id": "3EMXZxBXyyu5dWqbZ7NRta79GqbRkBCZbm3eP",
            "transaction_type": "place",
            "unofficial_currency_code": null,
            "website": null
        },
        {
            "account_id": "vovW6J5WEEcG1ZQ3DxE4CNaaeNNwGeiq6GmkG",
            "account_owner": null,
            "amount": -500.0,
            "authorized_date": "2025-07-16",
            "authorized_datetime": null,
            "category": null,
            "category_id": null,
            "check_number": null,
            "counterparties": [
                {
                    "name": "United Airlines",
                    "type": "merchant",
                    "website": "united.com",
                    "logo_url": "https://plaid-merchant-logos.plaid.com/united_airlines_1065.png",
                    "confidence_level": "VERY_HIGH",
                    "entity_id": "NKDjqyAdQQzpyeD8qpLnX0D6yvLe2KYKYYzQ4",
                    "phone_number": null
                }
            ],
            "date": "2025-07-16",
            "datetime": null,
            "iso_currency_code": "USD",
            "location": {
                "address": null,
                "city": null,
                "region": null,
                "postal_code": null,
                "country": null,
                "lat": null,
                "lon": null,
                "store_number": null
            },
            "logo_url": "https://plaid-merchant-logos.plaid.com/united_airlines_1065.png",
            "merchant_entity_id": "NKDjqyAdQQzpyeD8qpLnX0D6yvLe2KYKYYzQ4",
            "merchant_name": "United Airlines",
            "name": "United Airlines",
            "payment_channel": "in store",
            "payment_meta": {
                "reference_number": null,
                "ppd_id": null,
                "payee": null,
                "by_order_of": null,
                "payer": null,
                "payment_method": null,
                "payment_processor": null,
                "reason": null
            },
            "pending": false,
            "pending_transaction_id": null,
            "personal_finance_category": {
                "confidence_level": "VERY_HIGH",
                "detailed": "TRAVEL_FLIGHTS",
                "primary": "TRAVEL"
            },
            "personal_finance_category_icon_url": "https://plaid-category-icons.plaid.com/PFC_TRAVEL.png",
            "transaction_code": null,
            "transaction_id": "JjJNyWaNMMI7PQAbRkD5CJdEomGaQ6fBMQqvK",
            "transaction_type": "special",
            "unofficial_currency_code": null,
            "website": "united.com"
        },
        {
            "account_id": "vovW6J5WEEcG1ZQ3DxE4CNaaeNNwGeiq6GmkG",
            "account_owner": null,
            "amount": 12.0,
            "authorized_date": "2025-07-15",
            "authorized_datetime": null,
            "category": null,
            "category_id": null,
            "check_number": null,
            "counterparties": [
                {
                    "name": "McDonald's",
                    "type": "merchant",
                    "website": "mcdonalds.com",
                    "logo_url": "https://plaid-merchant-logos.plaid.com/mcdonalds_619.png",
                    "confidence_level": "VERY_HIGH",
                    "entity_id": "vzWXDWBjB06j5BJoD3Jo84OJZg7JJzmqOZA22",
                    "phone_number": null
                }
            ],
            "date": "2025-07-15",
            "datetime": null,
            "iso_currency_code": "USD",
            "location": {
                "address": null,
                "city": null,
                "region": null,
                "postal_code": null,
                "country": null,
                "lat": null,
                "lon": null,
                "store_number": "3322"
            },
            "logo_url": "https://plaid-merchant-logos.plaid.com/mcdonalds_619.png",
            "merchant_entity_id": "vzWXDWBjB06j5BJoD3Jo84OJZg7JJzmqOZA22",
            "merchant_name": "McDonald's",
            "name": "McDonald's",
            "payment_channel": "in store",
            "payment_meta": {
                "reference_number": null,
                "ppd_id": null,
                "payee": null,
                "by_order_of": null,
                "payer": null,
                "payment_method": null,
                "payment_processor": null,
                "reason": null
            },
            "pending": false,
            "pending_transaction_id": null,
            "personal_finance_category": {
                "confidence_level": "VERY_HIGH",
                "detailed": "FOOD_AND_DRINK_FAST_FOOD",
                "primary": "FOOD_AND_DRINK"
            },
            "personal_finance_category_icon_url": "https://plaid-category-icons.plaid.com/PFC_FOOD_AND_DRINK.png",
            "transaction_code": null,
            "transaction_id": "kNvQRobQ77sVE7onb361IaBvKWPM31CLDJKer",
            "transaction_type": "place",
            "unofficial_currency_code": null,
            "website": "mcdonalds.com"
        },
        {
            "account_id": "vovW6J5WEEcG1ZQ3DxE4CNaaeNNwGeiq6GmkG",
            "account_owner": null,
            "amount": 4.33,
            "authorized_date": "2025-07-15",
            "authorized_datetime": null,
            "category": null,
            "category_id": null,
            "check_number": null,
            "counterparties": [
                {
                    "name": "Starbucks",
                    "type": "merchant",
                    "website": "starbucks.com",
                    "logo_url": "https://plaid-merchant-logos.plaid.com/starbucks_956.png",
                    "confidence_level": "VERY_HIGH",
                    "entity_id": "NZAJQ5wYdo1W1p39X5q5gpb15OMe39pj4pJBb",
                    "phone_number": null
                }
            ],
            "date": "2025-07-15",
            "datetime": null,
            "iso_currency_code": "USD",
            "location": {
                "address": null,
                "city": null,
                "region": null,
                "postal_code": null,
                "country": null,
                "lat": null,
                "lon": null,
                "store_number": null
            },
            "logo_url": "https://plaid-merchant-logos.plaid.com/starbucks_956.png",
            "merchant_entity_id": "NZAJQ5wYdo1W1p39X5q5gpb15OMe39pj4pJBb",
            "merchant_name": "Starbucks",
            "name": "Starbucks",
            "payment_channel": "in store",
            "payment_meta": {
                "reference_number": null,
                "ppd_id": null,
                "payee": null,
                "by_order_of": null,
                "payer": null,
                "payment_method": null,
                "payment_processor": null,
                "reason": null
            },
            "pending": false,
            "pending_transaction_id": null,
            "personal_finance_category": {
                "confidence_level": "VERY_HIGH",
                "detailed": "FOOD_AND_DRINK_COFFEE",
                "primary": "FOOD_AND_DRINK"
            },
            "personal_finance_category_icon_url": "https://plaid-category-icons.plaid.com/PFC_FOOD_AND_DRINK.png",
            "transaction_code": null,
            "transaction_id": "lP6QRoWQeehMENVr53GlCdXy6PR7NDFpga8eL",
            "transaction_type": "place",
            "unofficial_currency_code": null,
            "website": "starbucks.com"
        },
        {
            "account_id": "vovW6J5WEEcG1ZQ3DxE4CNaaeNNwGeiq6GmkG",
            "account_owner": null,
            "amount": 89.4,
            "authorized_date": "2025-07-13",
            "authorized_datetime": null,
            "category": null,
            "category_id": null,
            "check_number": null,
            "counterparties": [
                {
                    "name": "FUN",
                    "type": "merchant",
                    "website": null,
                    "logo_url": null,
                    "confidence_level": "LOW",
                    "entity_id": null,
                    "phone_number": null
                }
            ],
            "date": "2025-07-14",
            "datetime": null,
            "iso_currency_code": "USD",
            "location": {
                "address": null,
                "city": null,
                "region": null,
                "postal_code": null,
                "country": null,
                "lat": null,
                "lon": null,
                "store_number": null
            },
            "logo_url": null,
            "merchant_entity_id": null,
            "merchant_name": "FUN",
            "name": "SparkFun",
            "payment_channel": "in store",
            "payment_meta": {
                "reference_number": null,
                "ppd_id": null,
                "payee": null,
                "by_order_of": null,
                "payer": null,
                "payment_method": null,
                "payment_processor": null,
                "reason": null
            },
            "pending": false,
            "pending_transaction_id": null,
            "personal_finance_category": {
                "confidence_level": "LOW",
                "detailed": "GENERAL_MERCHANDISE_OTHER_GENERAL_MERCHANDISE",
                "primary": "GENERAL_MERCHANDISE"
            },
            "personal_finance_category_icon_url": "https://plaid-category-icons.plaid.com/PFC_GENERAL_MERCHANDISE.png",
            "transaction_code": null,
            "transaction_id": "qZv16oX1LLhgwz7pqMWnuM4gdDrL5GugP6k1d",
            "transaction_type": "place",
            "unofficial_currency_code": null,
            "website": null
        },
        {
            "account_id": "RpqylAVyWWSnKEkZG9Q5CqJJgqq4pgiapxyb7",
            "account_owner": null,
            "amount": -4.22,
            "authorized_date": "2025-07-13",
            "authorized_datetime": null,
            "category": null,
            "category_id": null,
            "check_number": null,
            "counterparties": [],
            "date": "2025-07-13",
            "datetime": null,
            "iso_currency_code": "USD",
            "location": {
                "address": null,
                "city": null,
                "region": null,
                "postal_code": null,
                "country": null,
                "lat": null,
                "lon": null,
                "store_number": null
            },
            "logo_url": null,
            "merchant_entity_id": null,
            "merchant_name": null,
            "name": "INTRST PYMNT",
            "payment_channel": "other",
            "payment_meta": {
                "reference_number": null,
                "ppd_id": null,
                "payee": null,
                "by_order_of": null,
                "payer": null,
                "payment_method": null,
                "payment_processor": null,
                "reason": null
            },
            "pending": false,
            "pending_transaction_id": null,
            "personal_finance_category": {
                "confidence_level": "LOW",
                "detailed": "INCOME_WAGES",
                "primary": "INCOME"
            },
            "personal_finance_category_icon_url": "https://plaid-category-icons.plaid.com/PFC_INCOME.png",
            "transaction_code": null,
            "transaction_id": "zWvw61MwkkIBb45lo9MkhmBRELXDKdclB3W1w",
            "transaction_type": "special",
            "unofficial_currency_code": null,
            "website": null
        },
        {
            "account_id": "XAxV3R1VyyTaAqv3K9blCXBBpXXvepCbKMZnd",
            "account_owner": null,
            "amount": 500.0,
            "authorized_date": null,
            "authorized_datetime": null,
            "category": null,
            "category_id": null,
            "check_number": null,
            "counterparties": [
                {
                    "name": "United Airlines",
                    "type": "merchant",
                    "website": "united.com",
                    "logo_url": "https://plaid-merchant-logos.plaid.com/united_airlines_1065.png",
                    "confidence_level": "VERY_HIGH",
                    "entity_id": "NKDjqyAdQQzpyeD8qpLnX0D6yvLe2KYKYYzQ4",
                    "phone_number": null
                }
            ],
            "date": "2025-07-03",
            "datetime": null,
            "iso_currency_code": "USD",
            "location": {
                "address": null,
                "city": null,
                "region": null,
                "postal_code": null,
                "country": null,
                "lat": null,
                "lon": null,
                "store_number": null
            },
            "logo_url": "https://plaid-merchant-logos.plaid.com/united_airlines_1065.png",
            "merchant_entity_id": "NKDjqyAdQQzpyeD8qpLnX0D6yvLe2KYKYYzQ4",
            "merchant_name": "United Airlines",
            "name": "United Airlines",
            "payment_channel": "in store",
            "payment_meta": {
                "reference_number": null,
                "ppd_id": null,
                "payee": null,
                "by_order_of": null,
                "payer": null,
                "payment_method": null,
                "payment_processor": null,
                "reason": null
            },
            "pending": false,
            "pending_transaction_id": null,
            "personal_finance_category": {
                "confidence_level": "VERY_HIGH",
                "detailed": "TRAVEL_FLIGHTS",
                "primary": "TRAVEL"
            },
            "personal_finance_category_icon_url": "https://plaid-category-icons.plaid.com/PFC_TRAVEL.png",
            "transaction_code": null,
            "transaction_id": "x8vW6mBWAASbVA7WQdXPi5A8kNzvZxc6PyvRk",
            "transaction_type": "special",
            "unofficial_currency_code": null,
            "website": "united.com"
        },
        {
            "account_id": "vovW6J5WEEcG1ZQ3DxE4CNaaeNNwGeiq6GmkG",
            "account_owner": null,
            "amount": 6.33,
            "authorized_date": "2025-06-30",
            "authorized_datetime": null,
            "category": null,
            "category_id": null,
            "check_number": null,
            "counterparties": [
                {
                    "name": "Uber",
                    "type": "merchant",
                    "website": "uber.com",
                    "logo_url": "https://plaid-merchant-logos.plaid.com/uber_1060.png",
                    "confidence_level": "VERY_HIGH",
                    "entity_id": "eyg8o776k0QmNgVpAmaQj4WgzW9Qzo6O51gdd",
                    "phone_number": null
                }
            ],
            "date": "2025-07-01",
            "datetime": null,
            "iso_currency_code": "USD",
            "location": {
                "address": null,
                "city": null,
                "region": null,
                "postal_code": null,
                "country": null,
                "lat": null,
                "lon": null,
                "store_number": null
            },
            "logo_url": "https://plaid-merchant-logos.plaid.com/uber_1060.png",
            "merchant_entity_id": "eyg8o776k0QmNgVpAmaQj4WgzW9Qzo6O51gdd",
            "merchant_name": "Uber",
            "name": "Uber 072515 SF**POOL**",
            "payment_channel": "online",
            "payment_meta": {
                "reference_number": null,
                "ppd_id": null,
                "payee": null,
                "by_order_of": null,
                "payer": null,
                "payment_method": null,
                "payment_processor": null,
                "reason": null
            },
            "pending": false,
            "pending_transaction_id": null,
            "personal_finance_category": {
                "confidence_level": "VERY_HIGH",
                "detailed": "TRANSPORTATION_TAXIS_AND_RIDE_SHARES",
                "primary": "TRANSPORTATION"
            },
            "personal_finance_category_icon_url": "https://plaid-category-icons.plaid.com/PFC_TRANSPORTATION.png",
            "transaction_code": null,
            "transaction_id": "K7JNLWaN11FrjGownRp5HzKVbLjXEeuRkEbaR",
            "transaction_type": "special",
            "unofficial_currency_code": null,
            "website": "uber.com"
        },
        {
            "account_id": "XAxV3R1VyyTaAqv3K9blCXBBpXXvepCbKMZnd",
            "account_owner": null,
            "amount": 500.0,
            "authorized_date": null,
            "authorized_datetime": null,
            "category": null,
            "category_id": null,
            "check_number": null,
            "counterparties": [],
            "date": "2025-06-28",
            "datetime": null,
            "iso_currency_code": "USD",
            "location": {
                "address": null,
                "city": null,
                "region": null,
                "postal_code": null,
                "country": null,
                "lat": null,
                "lon": null,
                "store_number": null
            },
            "logo_url": null,
            "merchant_entity_id": null,
            "merchant_name": null,
            "name": "Tectra Inc",
            "payment_channel": "in store",
            "payment_meta": {
                "reference_number": null,
                "ppd_id": null,
                "payee": null,
                "by_order_of": null,
                "payer": null,
                "payment_method": null,
                "payment_processor": null,
                "reason": null
            },
            "pending": false,
            "pending_transaction_id": null,
            "personal_finance_category": {
                "confidence_level": "LOW",
                "detailed": "ENTERTAINMENT_SPORTING_EVENTS_AMUSEMENT_PARKS_AND_MUSEUMS",
                "primary": "ENTERTAINMENT"
            },
            "personal_finance_category_icon_url": "https://plaid-category-icons.plaid.com/PFC_ENTERTAINMENT.png",
            "transaction_code": null,
            "transaction_id": "dz13R9d3xxI4oq9PpgkWckXN4vm7BxsJzBexX",
            "transaction_type": "place",
            "unofficial_currency_code": null,
            "website": null
        },
        {
            "account_id": "XAxV3R1VyyTaAqv3K9blCXBBpXXvepCbKMZnd",
            "account_owner": null,
            "amount": 2078.5,
            "authorized_date": null,
            "authorized_datetime": null,
            "category": null,
            "category_id": null,
            "check_number": null,
            "counterparties": [],
            "date": "2025-06-27",
            "datetime": null,
            "iso_currency_code": "USD",
            "location": {
                "address": null,
                "city": null,
                "region": null,
                "postal_code": null,
                "country": null,
                "lat": null,
                "lon": null,
                "store_number": null
            },
            "logo_url": null,
            "merchant_entity_id": null,
            "merchant_name": null,
            "name": "AUTOMATIC PAYMENT - THANK",
            "payment_channel": "online",
            "payment_meta": {
                "reference_number": null,
                "ppd_id": null,
                "payee": null,
                "by_order_of": null,
                "payer": null,
                "payment_method": null,
                "payment_processor": null,
                "reason": null
            },
            "pending": false,
            "pending_transaction_id": null,
            "personal_finance_category": {
                "confidence_level": "LOW",
                "detailed": "GENERAL_MERCHANDISE_OTHER_GENERAL_MERCHANDISE",
                "primary": "GENERAL_MERCHANDISE"
            },
            "personal_finance_category_icon_url": "https://plaid-category-icons.plaid.com/PFC_GENERAL_MERCHANDISE.png",
            "transaction_code": null,
            "transaction_id": "NZJjLywjooh9WmJRgkw5CGabmvzWX9iypXmqN",
            "transaction_type": "special",
            "unofficial_currency_code": null,
            "website": null
        },
        {
            "account_id": "XAxV3R1VyyTaAqv3K9blCXBBpXXvepCbKMZnd",
            "account_owner": null,
            "amount": 500.0,
            "authorized_date": null,
            "authorized_datetime": null,
            "category": null,
            "category_id": null,
            "check_number": null,
            "counterparties": [
                {
                    "name": "KFC",
                    "type": "merchant",
                    "website": "kfc.com",
                    "logo_url": "https://plaid-merchant-logos.plaid.com/kfc_546.png",
                    "confidence_level": "VERY_HIGH",
                    "entity_id": "3LmdknrdwVy9vm0dqj417rLKeJXW7veV7eb2e",
                    "phone_number": null
                }
            ],
            "date": "2025-06-27",
            "datetime": null,
            "iso_currency_code": "USD",
            "location": {
                "address": null,
                "city": null,
                "region": null,
                "postal_code": null,
                "country": null,
                "lat": null,
                "lon": null,
                "store_number": null
            },
            "logo_url": "https://plaid-merchant-logos.plaid.com/kfc_546.png",
            "merchant_entity_id": "3LmdknrdwVy9vm0dqj417rLKeJXW7veV7eb2e",
            "merchant_name": "KFC",
            "name": "KFC",
            "payment_channel": "in store",
            "payment_meta": {
                "reference_number": null,
                "ppd_id": null,
                "payee": null,
                "by_order_of": null,
                "payer": null,
                "payment_method": null,
                "payment_processor": null,
                "reason": null
            },
            "pending": false,
            "pending_transaction_id": null,
            "personal_finance_category": {
                "confidence_level": "VERY_HIGH",
                "detailed": "FOOD_AND_DRINK_FAST_FOOD",
                "primary": "FOOD_AND_DRINK"
            },
            "personal_finance_category_icon_url": "https://plaid-category-icons.plaid.com/PFC_FOOD_AND_DRINK.png",
            "transaction_code": null,
            "transaction_id": "4W1kAdvk99I1pqKAJb5Ec4q69AxoXaCJVl7w4",
            "transaction_type": "place",
            "unofficial_currency_code": null,
            "website": "kfc.com"
        },
        {
            "account_id": "XAxV3R1VyyTaAqv3K9blCXBBpXXvepCbKMZnd",
            "account_owner": null,
            "amount": 500.0,
            "authorized_date": null,
            "authorized_datetime": null,
            "category": null,
            "category_id": null,
            "check_number": null,
            "counterparties": [],
            "date": "2025-06-27",
            "datetime": null,
            "iso_currency_code": "USD",
            "location": {
                "address": null,
                "city": null,
                "region": null,
                "postal_code": null,
                "country": null,
                "lat": null,
                "lon": null,
                "store_number": null
            },
            "logo_url": null,
            "merchant_entity_id": null,
            "merchant_name": null,
            "name": "Madison Bicycle Shop",
            "payment_channel": "in store",
            "payment_meta": {
                "reference_number": null,
                "ppd_id": null,
                "payee": null,
                "by_order_of": null,
                "payer": null,
                "payment_method": null,
                "payment_processor": null,
                "reason": null
            },
            "pending": false,
            "pending_transaction_id": null,
            "personal_finance_category": {
                "confidence_level": "LOW",
                "detailed": "GENERAL_MERCHANDISE_SPORTING_GOODS",
                "primary": "GENERAL_MERCHANDISE"
            },
            "personal_finance_category_icon_url": "https://plaid-category-icons.plaid.com/PFC_GENERAL_MERCHANDISE.png",
            "transaction_code": null,
            "transaction_id": "aqQrRGdrzzfxAjgDawKvF3VQxprgkyfZJkLxn",
            "transaction_type": "place",
            "unofficial_currency_code": null,
            "website": null
        }
    ],
    "total_transactions": 16,
    "item": {
        "item_id": "eBLxRDaxddHN5KDpb8GjHobLv8vmM3ULVmaZ1",
        "webhook": "",
        "error": null,
        "available_products": [
            "assets",
            "auth",
            "balance",
            "identity",
            "identity_match",
            "income_verification",
            "investments",
            "investments_auth",
            "liabilities",
            "recurring_transactions",
            "signal",
            "statements",
            "transfer"
        ],
        "billed_products": [
            "transactions"
        ],
        "consent_expiration_time": null,
        "update_type": "background",
        "institution_id": "ins_109508",
        "institution_name": "First Platypus Bank",
        "products": [
            "transactions"
        ]
    },
    "request_id": "X42g7iOKeeJpmAZ"
}